MANIFEST.in
README.md
setup.py
webplatform_auth/__init__.py
webplatform_auth/webplatform-auth
webplatform_auth.egg-info/PKG-INFO
webplatform_auth.egg-info/SOURCES.txt
webplatform_auth.egg-info/dependency_links.txt
webplatform_auth.egg-info/requires.txt
webplatform_auth.egg-info/top_level.txt
webplatform_auth/app/__init__.py
webplatform_auth/app/app.py
webplatform_auth/app/middleware/__init__.py
webplatform_auth/app/middleware/token.py
webplatform_auth/app/views/__init__.py
webplatform_auth/app/views/responses.py
webplatform_auth/app/views/saml.py
webplatform_auth/container/data/README.md
webplatform_auth/container/docker/actions/auth/build.sh
webplatform_auth/container/docker/actions/auth/entry.sh
webplatform_auth/container/docker/actions/auth/restart.sh
webplatform_auth/container/docker/actions/auth/start.sh
webplatform_auth/container/docker/actions/auth/stop.sh
webplatform_auth/container/docker/actions/auth/update.sh
webplatform_auth/container/docker/auth/gunicorn.py
webplatform_auth/container/docker/auth/saml/settings.json
webplatform_auth/container/docker/auth/saml/sp.crt
webplatform_auth/container/docker/auth/saml/sp.key
webplatform_auth/container/settings/auth.json
webplatform_auth/container/settings/cli.json
webplatform_auth/lib/BaseUser.py
webplatform_auth/lib/Session.py
webplatform_auth/lib/User.py
webplatform_auth/lib/__init__.py
webplatform_auth/lib/users/__init__.py
webplatform_auth/lib/users/change_user.py
webplatform_auth/lib/users/get.py
webplatform_auth/lib/users/list.py
webplatform_auth/lib/users/picture.py
webplatform_auth/lib/users/search.py
webplatform_auth/lib/users/timezone.py
webplatform_auth/lib/users/permissions/__init__.py
webplatform_auth/lib/users/permissions/add.py
webplatform_auth/lib/users/permissions/get.py
webplatform_auth/lib/users/permissions/list.py
webplatform_auth/lib/users/permissions/remove.py
webplatform_auth/lib/users/token/__init__.py
webplatform_auth/lib/users/token/renew.py