Metadata-Version: 1.2
Name: webplatform-auth
Version: 1.0.2
Summary: Authentication for webplatform
Home-page: https://github.com/lost-osiris/webplatform-auth
Author: Matthew Owens
Author-email: mowens@redhat.com
License: MIT
Platform: UNKNOWN
Classifier: Programming Language :: Python :: 3
Classifier: License :: OSI Approved :: MIT License
Classifier: Operating System :: OS Independent
Requires-Python: >=3
